CHANGES.txt
LICENSE.txt
MANIFEST.in
README.txt
setup.py
src/p01/__init__.py
src/p01.tester.egg-info/PKG-INFO
src/p01.tester.egg-info/SOURCES.txt
src/p01.tester.egg-info/dependency_links.txt
src/p01.tester.egg-info/namespace_packages.txt
src/p01.tester.egg-info/not-zip-safe
src/p01.tester.egg-info/requires.txt
src/p01.tester.egg-info/top_level.txt
src/p01/tester/README.txt
src/p01/tester/__init__.py
src/p01/tester/ajax.txt
src/p01/tester/browser.py
src/p01/tester/browser.txt
src/p01/tester/exceptions.py
src/p01/tester/qt_compat.py
src/p01/tester/server.py
src/p01/tester/server.txt
src/p01/tester/testing.py
src/p01/tester/tests.py
src/p01/tester/xpath.py
src/p01/tester/xpath.txt
src/p01/tester/source/jquery-1.8.1.js
src/p01/tester/source/jquery.simulate-r6063.js
src/p01/tester/source/post.js