Metadata-Version: 1.0
Name: p01.tester
Version: 0.5.0
Summary: Headless Selenium Webdriver test browser and application server
Home-page: http://pypi.python.org/pypi/p01.tester
Author: Roger Ineichen, Projekt01 GmbH
Author-email: dev@projekt01.ch
License: ZPL 2.1
Keywords: zope3 z3c p01 testing testrunner test headless brwoser Selenium Webdriver setup
Platform: UNKNOWN
Classifier: Development Status :: 4 - Beta
Classifier: Environment :: Web Environment
Classifier: Intended Audience :: Developers
Classifier: License :: OSI Approved :: Zope Public License
Classifier: Programming Language :: Python
Classifier: Natural Language :: English
Classifier: Operating System :: OS Independent
Classifier: Topic :: Internet :: WWW/HTTP
Classifier: Framework :: Zope3
